{"v":"5.9.0","fr":29.9700012207031,"ip":0,"op":361.000014703831,"w":2794,"h":1530,"nm":"Earth Page Kindness to Self 2","ddd":0,"assets":[{"id":"image_0","w":2794,"h":1530,"u":"images/","p":"img_0.png","e":0},{"id":"image_1","w":2794,"h":1530,"u":"images/","p":"img_1.jpg","e":0},{"id":"video_0","w":640,"h":360,"u":"images/","p":"vid_0.mp4","e":0}],"fonts":{"list":[{"fName":"MulishRoman-SemiBold","fFamily":"Mulish","fStyle":"ExtraLight","ascent":73.609243163839}]},"layers":[{"ddd":0,"ind":1,"ty":5,"nm":"Did You Leave Someone Behind? Could It Be You?","td":1,"sr":1,"ks":{"o":{"a":0,"k":100,"ix":11},"r":{"a":0,"k":0,"ix":10},"p":{"a":0,"k":[281.083,410.573,0],"ix":2,"l":2},"a":{"a":0,"k":[0,0,0],"ix":1,"l":2},"s":{"a":0,"k":[100,100,100],"ix":6,"l":2}},"ao":0,"t":{"d":{"k":[{"s":{"s":90,"f":"MulishRoman-SemiBold","t":"Did You Leave Someone Behind?\rCould It Be You?","ca":0,"j":0,"tr":12,"lh":89,"ls":2,"fc":[0.478,0.792,0.145],"sc":[1,1,1],"sw":0.00999999977648,"of":false},"t":0}]},"p":{},"m":{"g":1,"a":{"a":0,"k":[0,0],"ix":2}},"a":[]},"ip":0,"op":900.000036657751,"st":0,"bm":10},{"ddd":0,"ind":2,"ty":9,"nm":"VJ LOOP NEON Glowing Red Tunnel Abstract Background Video Simple Lines Pattern 4k Screensaver.mp4","cl":"mp4","tt":1,"refId":"video_0","sr":1,"ks":{"o":{"a":0,"k":100,"ix":11},"r":{"a":0,"k":0,"ix":10},"p":{"a":0,"k":[960,540,0],"ix":2,"l":2},"a":{"a":0,"k":[320,180,0],"ix":1,"l":2},"s":{"a":0,"k":[300,300,100],"ix":6,"l":2}},"ao":0,"ef":[{"ty":5,"nm":"Hue/Saturation","np":11,"mn":"ADBE HUE SATURATION","ix":1,"en":1,"ef":[{"ty":7,"nm":"Channel Control","mn":"ADBE HUE SATURATION-0002","ix":1,"v":{"a":0,"k":1,"ix":1}},{},{"ty":0,"nm":"Master Hue","mn":"ADBE HUE SATURATION-0004","ix":3,"v":{"a":0,"k":196,"ix":3}},{"ty":0,"nm":"Master Saturation","mn":"ADBE HUE SATURATION-0005","ix":4,"v":{"a":0,"k":0,"ix":4}},{"ty":0,"nm":"Master Lightness","mn":"ADBE HUE SATURATION-0006","ix":5,"v":{"a":0,"k":0,"ix":5}},{"ty":7,"nm":"Colorize","mn":"ADBE HUE SATURATION-0007","ix":6,"v":{"a":0,"k":0,"ix":6}},{"ty":0,"nm":"Colorize Hue","mn":"ADBE HUE SATURATION-0008","ix":7,"v":{"a":0,"k":0,"ix":7}},{"ty":0,"nm":"Colorize Saturation","mn":"ADBE HUE SATURATION-0009","ix":8,"v":{"a":0,"k":25,"ix":8}},{"ty":0,"nm":"Colorize Lightness","mn":"ADBE HUE SATURATION-0010","ix":9,"v":{"a":0,"k":0,"ix":9}}]},{"ty":5,"nm":"Glow","np":16,"mn":"ADBE Glo2","ix":2,"en":1,"ef":[{"ty":7,"nm":"Glow Based On","mn":"ADBE Glo2-0001","ix":1,"v":{"a":0,"k":2,"ix":1}},{"ty":0,"nm":"Glow Threshold","mn":"ADBE Glo2-0002","ix":2,"v":{"a":0,"k":25.5,"ix":2}},{"ty":0,"nm":"Glow Radius","mn":"ADBE Glo2-0003","ix":3,"v":{"a":0,"k":60,"ix":3}},{"ty":0,"nm":"Glow Intensity","mn":"ADBE Glo2-0004","ix":4,"v":{"a":0,"k":0.3,"ix":4}},{"ty":7,"nm":"Composite Original","mn":"ADBE Glo2-0005","ix":5,"v":{"a":0,"k":2,"ix":5}},{"ty":7,"nm":"Glow Operation","mn":"ADBE Glo2-0006","ix":6,"v":{"a":0,"k":3,"ix":6}},{"ty":7,"nm":"Glow Colors","mn":"ADBE Glo2-0007","ix":7,"v":{"a":0,"k":1,"ix":7}},{"ty":7,"nm":"Color Looping","mn":"ADBE Glo2-0008","ix":8,"v":{"a":0,"k":3,"ix":8}},{"ty":0,"nm":"Color Loops","mn":"ADBE Glo2-0009","ix":9,"v":{"a":0,"k":1,"ix":9}},{"ty":0,"nm":"Color Phase","mn":"ADBE Glo2-0010","ix":10,"v":{"a":0,"k":0,"ix":10}},{"ty":0,"nm":"A & B Midpoint","mn":"ADBE Glo2-0011","ix":11,"v":{"a":0,"k":0.5,"ix":11}},{"ty":2,"nm":"Color A","mn":"ADBE Glo2-0012","ix":12,"v":{"a":0,"k":[1,1,1,0],"ix":12}},{"ty":2,"nm":"Color B","mn":"ADBE Glo2-0013","ix":13,"v":{"a":0,"k":[0,0,0,0],"ix":13}},{"ty":7,"nm":"Glow Dimensions","mn":"ADBE Glo2-0014","ix":14,"v":{"a":0,"k":1,"ix":14}}]},{"ty":5,"nm":"Hue/Saturation 2","np":11,"mn":"ADBE HUE SATURATION","ix":3,"en":1,"ef":[{"ty":7,"nm":"Channel Control","mn":"ADBE HUE SATURATION-0002","ix":1,"v":{"a":0,"k":1,"ix":1}},{},{"ty":0,"nm":"Master Hue","mn":"ADBE HUE SATURATION-0004","ix":3,"v":{"a":0,"k":-213,"ix":3}},{"ty":0,"nm":"Master Saturation","mn":"ADBE HUE SATURATION-0005","ix":4,"v":{"a":0,"k":0,"ix":4}},{"ty":0,"nm":"Master Lightness","mn":"ADBE HUE SATURATION-0006","ix":5,"v":{"a":0,"k":47,"ix":5}},{"ty":7,"nm":"Colorize","mn":"ADBE HUE SATURATION-0007","ix":6,"v":{"a":0,"k":0,"ix":6}},{"ty":0,"nm":"Colorize Hue","mn":"ADBE HUE SATURATION-0008","ix":7,"v":{"a":0,"k":0,"ix":7}},{"ty":0,"nm":"Colorize Saturation","mn":"ADBE HUE SATURATION-0009","ix":8,"v":{"a":0,"k":25,"ix":8}},{"ty":0,"nm":"Colorize Lightness","mn":"ADBE HUE SATURATION-0010","ix":9,"v":{"a":0,"k":0,"ix":9}}]},{"ty":5,"nm":"Curves","np":4,"mn":"ADBE CurvesCustom","ix":4,"en":1,"ef":[{"ty":7,"nm":"Channel:","mn":"ADBE CurvesCustom-0002","ix":1,"v":{"a":0,"k":1,"ix":1}},{}]}],"ip":0,"op":319680.013020833,"st":0,"bm":0},{"ddd":0,"ind":3,"ty":2,"nm":"Earth Page Kindness to Self Flowers(0;00;05;01).psd","cl":"psd","refId":"image_0","sr":1,"ks":{"o":{"a":1,"k":[{"i":{"x":[0.667],"y":[1]},"o":{"x":[0.333],"y":[0]},"t":91,"s":[0]},{"i":{"x":[0.667],"y":[1]},"o":{"x":[0.333],"y":[0]},"t":134,"s":[100]},{"i":{"x":[0.667],"y":[1]},"o":{"x":[0.333],"y":[0]},"t":271,"s":[100]},{"t":313.000012748751,"s":[0]}],"ix":11},"r":{"a":0,"k":0,"ix":10},"p":{"a":0,"k":[-1634.797,810.829,0],"ix":2,"l":2},"a":{"a":0,"k":[1397,765,0],"ix":1,"l":2},"s":{"a":0,"k":[100,100,100],"ix":6,"l":2}},"ao":0,"ef":[{"ty":5,"nm":"Hue/Saturation","np":11,"mn":"ADBE HUE SATURATION","ix":1,"en":1,"ef":[{"ty":7,"nm":"Channel Control","mn":"ADBE HUE SATURATION-0002","ix":1,"v":{"a":0,"k":1,"ix":1}},{},{"ty":0,"nm":"Master Hue","mn":"ADBE HUE SATURATION-0004","ix":3,"v":{"a":0,"k":0,"ix":3}},{"ty":0,"nm":"Master Saturation","mn":"ADBE HUE SATURATION-0005","ix":4,"v":{"a":0,"k":0,"ix":4}},{"ty":0,"nm":"Master Lightness","mn":"ADBE HUE SATURATION-0006","ix":5,"v":{"a":0,"k":0,"ix":5}},{"ty":7,"nm":"Colorize","mn":"ADBE HUE SATURATION-0007","ix":6,"v":{"a":0,"k":0,"ix":6}},{"ty":0,"nm":"Colorize Hue","mn":"ADBE HUE SATURATION-0008","ix":7,"v":{"a":0,"k":0,"ix":7}},{"ty":0,"nm":"Colorize Saturation","mn":"ADBE HUE SATURATION-0009","ix":8,"v":{"a":0,"k":25,"ix":8}},{"ty":0,"nm":"Colorize Lightness","mn":"ADBE HUE SATURATION-0010","ix":9,"v":{"a":0,"k":0,"ix":9}}]},{"ty":5,"nm":"Hue/Saturation 2","np":11,"mn":"ADBE HUE SATURATION","ix":2,"en":1,"ef":[{"ty":7,"nm":"Channel Control","mn":"ADBE HUE SATURATION-0002","ix":1,"v":{"a":0,"k":1,"ix":1}},{},{"ty":0,"nm":"Master Hue","mn":"ADBE HUE SATURATION-0004","ix":3,"v":{"a":0,"k":0,"ix":3}},{"ty":0,"nm":"Master Saturation","mn":"ADBE HUE SATURATION-0005","ix":4,"v":{"a":0,"k":0,"ix":4}},{"ty":0,"nm":"Master Lightness","mn":"ADBE HUE SATURATION-0006","ix":5,"v":{"a":0,"k":0,"ix":5}},{"ty":7,"nm":"Colorize","mn":"ADBE HUE SATURATION-0007","ix":6,"v":{"a":0,"k":0,"ix":6}},{"ty":0,"nm":"Colorize Hue","mn":"ADBE HUE SATURATION-0008","ix":7,"v":{"a":0,"k":0,"ix":7}},{"ty":0,"nm":"Colorize Saturation","mn":"ADBE HUE SATURATION-0009","ix":8,"v":{"a":0,"k":25,"ix":8}},{"ty":0,"nm":"Colorize Lightness","mn":"ADBE HUE SATURATION-0010","ix":9,"v":{"a":0,"k":0,"ix":9}}]},{"ty":5,"nm":"Curves","np":4,"mn":"ADBE CurvesCustom","ix":3,"en":1,"ef":[{"ty":7,"nm":"Channel:","mn":"ADBE CurvesCustom-0002","ix":1,"v":{"a":0,"k":1,"ix":1}},{}]}],"ip":0,"op":900.000036657751,"st":0,"bm":0},{"ddd":0,"ind":4,"ty":2,"nm":"Earth Page Kindness to Self.png","cl":"png","refId":"image_1","sr":1,"ks":{"o":{"a":0,"k":100,"ix":11},"r":{"a":0,"k":0,"ix":10},"p":{"a":0,"k":[1397,765,0],"ix":2,"l":2},"a":{"a":0,"k":[1397,765,0],"ix":1,"l":2},"s":{"a":0,"k":[100,100,100],"ix":6,"l":2}},"ao":0,"ef":[{"ty":5,"nm":"Paint","np":4,"mn":"ADBE Paint","ix":1,"en":1,"ef":[{"ty":7,"nm":"Paint on Transparent","mn":"ADBE Paint On Transparent","ix":1,"v":{"a":0,"k":0,"ix":1}},{"ty":"","nm":"Strokes","np":17,"mn":"ADBE Paint Group","ix":2,"en":1,"ef":[]}]}],"ip":0,"op":900.000036657751,"st":0,"bm":0}],"markers":[],"chars":[{"ch":"D","size":90,"style":"ExtraLight","w":75.4,"data":{"shapes":[{"ty":"gr","it":[{"ind":0,"ty":"sh","ix":1,"ks":{"a":0,"k":{"i":[[0,0],[-5.5,2.767],[-2.834,5.267],[0,7.467],[2.833,5.234],[5.5,2.734],[7.933,0],[0,0],[0,0]],"o":[[7.933,0],[5.5,-2.766],[2.833,-5.266],[0,-7.533],[-2.834,-5.233],[-5.5,-2.733],[0,0],[0,0],[0,0]],"v":[[32.7,0],[52.85,-4.15],[65.35,-16.2],[69.6,-35.3],[65.35,-54.45],[52.85,-66.4],[32.7,-70.5],[8.3,-70.5],[8.3,0]],"c":true},"ix":2},"nm":"D","mn":"ADBE Vector Shape - Group","hd":false},{"ind":1,"ty":"sh","ix":2,"ks":{"a":0,"k":{"i":[[0,0],[0,0],[-4.434,-4.366],[0,-8.933],[4.433,-4.4],[9.066,0],[0,0]],"o":[[0,0],[9.066,0],[4.433,4.367],[0,8.934],[-4.434,4.4],[0,0],[0,0]],"v":[[18.7,-61.8],[32.1,-61.8],[52.35,-55.25],[59,-35.3],[52.35,-15.3],[32.1,-8.7],[18.7,-8.7]],"c":true},"ix":2},"nm":"D","mn":"ADBE Vector Shape - Group","hd":false}],"nm":"D","np":5,"cix":2,"bm":0,"ix":1,"mn":"ADBE Vector Group","hd":false}]},"fFamily":"Mulish"},{"ch":"i","size":90,"style":"ExtraLight","w":24.9,"data":{"shapes":[{"ty":"gr","it":[{"ind":0,"ty":"sh","ix":1,"ks":{"a":0,"k":{"i":[[0,0],[0,0],[0,0],[0,0]],"o":[[0,0],[0,0],[0,0],[0,0]],"v":[[17.5,0],[17.5,-50.4],[7.4,-50.4],[7.4,0]],"c":true},"ix":2},"nm":"i","mn":"ADBE Vector Shape - Group","hd":false},{"ind":1,"ty":"sh","ix":2,"ks":{"a":0,"k":{"i":[[0,0],[0,0],[0,0],[0,0]],"o":[[0,0],[0,0],[0,0],[0,0]],"v":[[18.3,-60.9],[18.3,-71.4],[6.6,-71.4],[6.6,-60.9]],"c":true},"ix":2},"nm":"i","mn":"ADBE Vector Shape - Group","hd":false}],"nm":"i","np":5,"cix":2,"bm":0,"ix":1,"mn":"ADBE Vector Group","hd":false}]},"fFamily":"Mulish"},{"ch":"d","size":90,"style":"ExtraLight","w":60.9,"data":{"shapes":[{"ty":"gr","it":[{"ind":0,"ty":"sh","ix":1,"ks":{"a":0,"k":{"i":[[-3.267,2.2],[-1.134,3.8],[0,0],[0,0],[0,0],[0,0],[0,0],[0,0],[0,0],[3.3,2.167],[4.333,0],[3.366,-2.1],[1.833,-3.866],[0,-5.466],[-1.834,-3.933],[-3.367,-2.066],[-4.4,0]],"o":[[3.266,-2.2],[0,0],[0,0],[0,0],[0,0],[0,0],[0,0],[0,0],[-1.067,-3.733],[-3.3,-2.166],[-4.4,0],[-3.367,2.1],[-1.834,3.867],[0,5.4],[1.833,3.934],[3.366,2.067],[4.4,0]],"v":[[38.2,-2.4],[44.8,-11.4],[43.6,-11.4],[43.6,0],[53.6,0],[53.6,-73.6],[43.5,-73.6],[43.5,-39.2],[44.7,-39.2],[38.15,-48.05],[26.7,-51.3],[15.05,-48.15],[7.25,-39.2],[4.5,-25.2],[7.25,-11.2],[15.05,-2.2],[26.7,0.9]],"c":true},"ix":2},"nm":"d","mn":"ADBE Vector Shape - Group","hd":false},{"ind":1,"ty":"sh","ix":2,"ks":{"a":0,"k":{"i":[[2.633,3.067],[0,6],[-2.634,3.034],[-4.4,0],[-2.667,-3.033],[0,-6],[2.666,-3.066],[4.333,0]],"o":[[-2.634,-3.066],[0,-6],[2.633,-3.033],[4.333,0],[2.666,3.034],[0,6],[-2.667,3.067],[-4.4,0]],"v":[[18.65,-11.6],[14.7,-25.2],[18.65,-38.75],[29.2,-43.3],[39.7,-38.75],[43.7,-25.2],[39.7,-11.6],[29.2,-7]],"c":true},"ix":2},"nm":"d","mn":"ADBE Vector Shape - Group","hd":false}],"nm":"d","np":5,"cix":2,"bm":0,"ix":1,"mn":"ADBE Vector Group","hd":false}]},"fFamily":"Mulish"},{"ch":" ","size":90,"style":"ExtraLight","w":26.7,"data":{},"fFamily":"Mulish"},{"ch":"Y","size":90,"style":"ExtraLight","w":62,"data":{"shapes":[{"ty":"gr","it":[{"ind":0,"ty":"sh","ix":1,"ks":{"a":0,"k":{"i":[[0,0],[0,0],[0,0],[0,0],[0,0],[0,0],[0,0],[0,0],[0,0],[0,0],[0,0],[0,0]],"o":[[0,0],[0,0],[0,0],[0,0],[0,0],[0,0],[0,0],[0,0],[0,0],[0,0],[0,0],[0,0]],"v":[[36,0],[36,-33.1],[33.9,-26.5],[63.5,-70.5],[51.9,-70.5],[29.8,-36.8],[32.3,-36.8],[10.2,-70.5],[-1.8,-70.5],[27.9,-26.5],[25.6,-33.1],[25.6,0]],"c":true},"ix":2},"nm":"Y","mn":"ADBE Vector Shape - Group","hd":false}],"nm":"Y","np":3,"cix":2,"bm":0,"ix":1,"mn":"ADBE Vector Group","hd":false}]},"fFamily":"Mulish"},{"ch":"o","size":90,"style":"ExtraLight","w":58.1,"data":{"shapes":[{"ty":"gr","it":[{"ind":0,"ty":"sh","ix":1,"ks":{"a":0,"k":{"i":[[-3.7,2.1],[-2.034,3.9],[0,5.4],[2.033,3.9],[3.7,2.1],[5,0],[3.666,-2.1],[2,-3.9],[0,-5.4],[-2,-3.9],[-3.667,-2.1],[-5,0]],"o":[[3.7,-2.1],[2.033,-3.9],[0,-5.4],[-2.034,-3.9],[-3.7,-2.1],[-5,0],[-3.667,2.1],[-2,3.9],[0,5.4],[2,3.9],[3.666,2.1],[5,0]],"v":[[42.05,-2.25],[50.65,-11.25],[53.7,-25.2],[50.65,-39.15],[42.05,-48.15],[29,-51.3],[16,-48.15],[7.5,-39.15],[4.5,-25.2],[7.5,-11.25],[16,-2.25],[29,0.9]],"c":true},"ix":2},"nm":"o","mn":"ADBE Vector Shape - Group","hd":false},{"ind":1,"ty":"sh","ix":2,"ks":{"a":0,"k":{"i":[[2.6,3.067],[0,6],[-2.6,3.034],[-4.334,0],[-2.6,-3.033],[0,-6],[2.6,-3.066],[4.4,0]],"o":[[-2.6,-3.066],[0,-6],[2.6,-3.033],[4.4,0],[2.6,3.034],[0,6],[-2.6,3.067],[-4.334,0]],"v":[[18.6,-11.6],[14.7,-25.2],[18.6,-38.75],[29,-43.3],[39.5,-38.75],[43.4,-25.2],[39.5,-11.6],[29,-7]],"c":true},"ix":2},"nm":"o","mn":"ADBE Vector Shape - Group","hd":false}],"nm":"o","np":5,"cix":2,"bm":0,"ix":1,"mn":"ADBE Vector Group","hd":false}]},"fFamily":"Mulish"},{"ch":"u","size":90,"style":"ExtraLight","w":58.6,"data":{"shapes":[{"ty":"gr","it":[{"ind":0,"ty":"sh","ix":1,"ks":{"a":0,"k":{"i":[[-3.067,2.034],[-1.4,3.734],[0,0],[0,0],[0,0],[0,0],[0,0],[0,0],[2.466,-2.666],[4,0],[1.733,2],[0,4.2],[0,0],[0,0],[0,0],[-3.034,-3.3],[-6.067,0]],"o":[[3.066,-2.033],[0,0],[0,0],[0,0],[0,0],[0,0],[0,0],[0,4.4],[-2.467,2.667],[-3.534,0],[-1.734,-2],[0,0],[0,0],[0,0],[0,6.867],[3.033,3.3],[4.066,0]],"v":[[36,-2.15],[42.7,-10.8],[41.4,-10.8],[41.4,0],[51.2,0],[51.2,-50.4],[41.1,-50.4],[41.1,-21.8],[37.4,-11.2],[27.7,-7.2],[19.8,-10.2],[17.2,-19.5],[17.2,-50.4],[7.1,-50.4],[7.1,-19.3],[11.65,-4.05],[25.3,0.9]],"c":true},"ix":2},"nm":"u","mn":"ADBE Vector Shape - Group","hd":false}],"nm":"u","np":3,"cix":2,"bm":0,"ix":1,"mn":"ADBE Vector Group","hd":false}]},"fFamily":"Mulish"},{"ch":"L","size":90,"style":"ExtraLight","w":55.2,"data":{"shapes":[{"ty":"gr","it":[{"ind":0,"ty":"sh","ix":1,"ks":{"a":0,"k":{"i":[[0,0],[0,0],[0,0],[0,0],[0,0],[0,0]],"o":[[0,0],[0,0],[0,0],[0,0],[0,0],[0,0]],"v":[[53.3,0],[53.3,-8.9],[18.7,-8.9],[18.7,-70.5],[8.3,-70.5],[8.3,0]],"c":true},"ix":2},"nm":"L","mn":"ADBE Vector Shape - Group","hd":false}],"nm":"L","np":3,"cix":2,"bm":0,"ix":1,"mn":"ADBE Vector Group","hd":false}]},"fFamily":"Mulish"},{"ch":"e","size":90,"style":"ExtraLight","w":54.6,"data":{"shapes":[{"ty":"gr","it":[{"ind":0,"ty":"sh","ix":1,"ks":{"a":0,"k":{"i":[[-3.334,1.1],[-2.334,2.067],[0,0],[2.566,-0.833],[2.933,0],[2.9,3],[0,5.934],[0,0],[-2.534,3.234],[-4.667,0],[-2.234,-2.766],[0,-5],[0,0],[0,0],[0,0],[0,0],[0,0],[1.666,3.634],[3.2,2],[4.733,0],[3.633,-2.166],[2.033,-3.933],[0,-5.266],[-4.667,-4.6],[-8.134,0]],"o":[[3.333,-1.1],[0,0],[-2.334,1.934],[-2.567,0.834],[-5.334,0],[-2.9,-3],[0,0],[0,-5.666],[2.533,-3.233],[4.2,0],[2.233,2.767],[0,0],[0,0],[0,0],[0,0],[0,0],[0,-4.933],[-1.667,-3.633],[-3.2,-2],[-4.8,0],[-3.634,2.167],[-2.034,3.934],[0,8.134],[4.666,4.6],[3.733,0]],"v":[[41.3,-0.75],[49.8,-5.5],[46.5,-12.4],[39.15,-8.25],[30.9,-7],[18.55,-11.5],[14.2,-24.9],[14.2,-25.9],[18,-39.25],[28.8,-44.1],[38.45,-39.95],[41.8,-28.3],[43.5,-29.6],[12.4,-29.6],[12.4,-23.8],[50.4,-23.8],[50.4,-27],[47.9,-39.85],[40.6,-48.3],[28.7,-51.3],[16.05,-48.05],[7.55,-38.9],[4.5,-25.1],[11.5,-6],[30.7,0.9]],"c":true},"ix":2},"nm":"e","mn":"ADBE Vector Shape - Group","hd":false}],"nm":"e","np":3,"cix":2,"bm":0,"ix":1,"mn":"ADBE Vector Group","hd":false}]},"fFamily":"Mulish"},{"ch":"a","size":90,"style":"ExtraLight","w":60.9,"data":{"shapes":[{"ty":"gr","it":[{"ind":0,"ty":"sh","ix":1,"ks":{"a":0,"k":{"i":[[-3.3,2.167],[-1.067,3.734],[0,0],[0,0],[0,0],[0,0],[-0.167,2.034],[-0.2,2.067],[0,0],[0,0],[0,0],[3.266,2.2],[4.4,0],[3.333,-2.1],[1.833,-3.866],[0,-5.466],[-1.834,-3.933],[-3.334,-2.066],[-4.467,0]],"o":[[3.3,-2.166],[0,0],[0,0],[0,0],[0,0],[0,-1.933],[0.166,-2.033],[0,0],[0,0],[0,0],[-1.067,-3.8],[-3.267,-2.2],[-4.467,0],[-3.334,2.1],[-1.834,3.867],[0,5.4],[1.833,3.934],[3.333,2.067],[4.266,0]],"v":[[38.05,-2.35],[44.6,-11.2],[43.5,-11.2],[43.5,0],[53.6,0],[53.6,-38.3],[53.85,-44.25],[54.4,-50.4],[44.6,-50.4],[43.6,-39],[44.7,-39],[38.2,-48],[26.7,-51.3],[15,-48.15],[7.25,-39.2],[4.5,-25.2],[7.25,-11.2],[15,-2.2],[26.7,0.9]],"c":true},"ix":2},"nm":"a","mn":"ADBE Vector Shape - Group","hd":false},{"ind":1,"ty":"sh","ix":2,"ks":{"a":0,"k":{"i":[[2.6,3.067],[0,6],[-2.634,3.034],[-4.4,0],[-2.634,-3.033],[0,-6],[2.633,-3.066],[4.333,0]],"o":[[-2.6,-3.066],[0,-6],[2.633,-3.033],[4.333,0],[2.633,3.034],[0,6],[-2.634,3.067],[-4.467,0]],"v":[[18.6,-11.6],[14.7,-25.2],[18.65,-38.75],[29.2,-43.3],[39.65,-38.75],[43.6,-25.2],[39.65,-11.6],[29.2,-7]],"c":true},"ix":2},"nm":"a","mn":"ADBE Vector Shape - Group","hd":false}],"nm":"a","np":5,"cix":2,"bm":0,"ix":1,"mn":"ADBE Vector Group","hd":false}]},"fFamily":"Mulish"},{"ch":"v","size":90,"style":"ExtraLight","w":55.5,"data":{"shapes":[{"ty":"gr","it":[{"ind":0,"ty":"sh","ix":1,"ks":{"a":0,"k":{"i":[[0,0],[0,0],[0,0],[0,0],[0,0],[0,0],[0,0],[0,0]],"o":[[0,0],[0,0],[0,0],[0,0],[0,0],[0,0],[0,0],[0,0]],"v":[[31.4,0],[53.1,-50.4],[42.8,-50.4],[25.5,-8.3],[28.4,-8.3],[11.4,-50.4],[0.6,-50.4],[22.2,0]],"c":true},"ix":2},"nm":"v","mn":"ADBE Vector Shape - Group","hd":false}],"nm":"v","np":3,"cix":2,"bm":0,"ix":1,"mn":"ADBE Vector Group","hd":false}]},"fFamily":"Mulish"},{"ch":"S","size":90,"style":"ExtraLight","w":63.3,"data":{"shapes":[{"ty":"gr","it":[{"ind":0,"ty":"sh","ix":1,"ks":{"a":0,"k":{"i":[[-4,1.7],[-2.167,3.067],[0,4.067],[3.2,2.9],[6.733,1.4],[0,0],[1.833,1.667],[0,2.934],[-2.9,2.134],[-5.134,0],[-3.4,-1.233],[-3,-2.6],[0,0],[4.2,1.434],[5,0],[4.033,-1.733],[2.266,-3.2],[0,-4.266],[-3.167,-3.033],[-6.467,-1.333],[0,0],[-1.834,-1.533],[0,-2.8],[2.633,-2],[5.6,0],[2.766,0.567],[2.433,1.134],[2.266,1.734],[0,0],[-4.6,-1.433],[-5.667,0]],"o":[[4,-1.7],[2.166,-3.066],[0,-5.066],[-3.2,-2.9],[0,0],[-4.267,-0.866],[-1.834,-1.666],[0,-3.666],[2.9,-2.133],[4.333,0],[3.4,1.234],[0,0],[-2.867,-2.8],[-4.2,-1.433],[-5.4,0],[-4.034,1.734],[-2.267,3.2],[0,5.267],[3.166,3.034],[0,0],[4.6,0.934],[1.833,1.534],[0,3.267],[-2.634,2],[-3.267,0],[-2.767,-0.566],[-2.434,-1.133],[0,0],[3.4,2.667],[4.6,1.433],[5.466,0]],"v":[[46.3,-1.65],[55.55,-8.8],[58.8,-19.5],[54,-31.45],[39.1,-37.9],[28.2,-40],[19.05,-43.8],[16.3,-50.7],[20.65,-59.4],[32.7,-62.6],[44.3,-60.75],[53.9,-55],[57.3,-62.9],[46.7,-69.25],[32.9,-71.4],[18.75,-68.8],[9.3,-61.4],[5.9,-50.2],[10.65,-37.75],[25.1,-31.2],[36,-29],[45.65,-25.3],[48.4,-18.8],[44.45,-10.9],[32.1,-7.9],[23.05,-8.75],[15.25,-11.3],[8.2,-15.6],[4.7,-7.4],[16.7,-1.25],[32.1,0.9]],"c":true},"ix":2},"nm":"S","mn":"ADBE Vector Shape - Group","hd":false}],"nm":"S","np":3,"cix":2,"bm":0,"ix":1,"mn":"ADBE Vector Group","hd":false}]},"fFamily":"Mulish"},{"ch":"m","size":90,"style":"ExtraLight","w":88.8,"data":{"shapes":[{"ty":"gr","it":[{"ind":0,"ty":"sh","ix":1,"ks":{"a":0,"k":{"i":[[0,0],[0,0],[-2.2,2.667],[-3.867,0],[-1.5,-1.966],[0,-4.4],[0,0],[0,0],[0,0],[-2.267,2.667],[-3.867,0],[-1.5,-1.966],[0,-4.4],[0,0],[0,0],[0,0],[2.8,3.267],[5.6,0],[3.2,-2.166],[1.333,-3.666],[0,0],[2.633,1.967],[4.133,0],[2.9,-2],[1.4,-3.666],[0,0],[0,0],[0,0],[-0.167,-2.033],[0,-1.933],[0,0]],"o":[[0,0],[0,-4.533],[2.2,-2.666],[3.333,0],[1.5,1.967],[0,0],[0,0],[0,0],[0,-4.533],[2.266,-2.666],[3.333,0],[1.5,1.967],[0,0],[0,0],[0,0],[0,-6.866],[-2.8,-3.266],[-4.2,0],[-3.2,2.167],[0,0],[-1,-4.066],[-2.634,-1.966],[-4.067,0],[-2.9,2],[0,0],[0,0],[0,0],[0.2,2.067],[0.166,2.034],[0,0],[0,0]],"v":[[17.5,0],[17.5,-28.4],[20.8,-39.2],[29.9,-43.2],[37.15,-40.25],[39.4,-30.7],[39.4,0],[49.5,0],[49.5,-28.4],[52.9,-39.2],[62.1,-43.2],[69.35,-40.25],[71.6,-30.7],[71.6,0],[81.7,0],[81.7,-31.2],[77.5,-46.4],[64.9,-51.3],[53.8,-48.05],[47,-39.3],[48.6,-39.3],[43.15,-48.35],[33,-51.3],[22.55,-48.3],[16.1,-39.8],[17.3,-39.8],[16.4,-50.4],[6.6,-50.4],[7.15,-44.25],[7.4,-38.3],[7.4,0]],"c":true},"ix":2},"nm":"m","mn":"ADBE Vector Shape - Group","hd":false}],"nm":"m","np":3,"cix":2,"bm":0,"ix":1,"mn":"ADBE Vector Group","hd":false}]},"fFamily":"Mulish"},{"ch":"n","size":90,"style":"ExtraLight","w":59.3,"data":{"shapes":[{"ty":"gr","it":[{"ind":0,"ty":"sh","ix":1,"ks":{"a":0,"k":{"i":[[0,0],[0,0],[-2.534,2.634],[-4.267,0],[-1.767,-1.966],[0,-4.466],[0,0],[0,0],[0,0],[3.033,3.267],[5.933,0],[3.2,-1.966],[1.533,-3.733],[0,0],[0,0],[0,0],[-0.167,-2.033],[0,-1.933],[0,0]],"o":[[0,0],[0,-4.466],[2.533,-2.633],[3.6,0],[1.766,1.967],[0,0],[0,0],[0,0],[0,-6.866],[-3.034,-3.266],[-4.2,0],[-3.2,1.967],[0,0],[0,0],[0,0],[0.2,2.067],[0.166,2.034],[0,0],[0,0]],"v":[[17.5,0],[17.5,-28.6],[21.3,-39.25],[31.5,-43.2],[39.55,-40.25],[42.2,-30.6],[42.2,0],[52.3,0],[52.3,-31.2],[47.75,-46.4],[34.3,-51.3],[23.2,-48.35],[16.1,-39.8],[17.3,-39.8],[16.4,-50.4],[6.6,-50.4],[7.15,-44.25],[7.4,-38.3],[7.4,0]],"c":true},"ix":2},"nm":"n","mn":"ADBE Vector Shape - Group","hd":false}],"nm":"n","np":3,"cix":2,"bm":0,"ix":1,"mn":"ADBE Vector Group","hd":false}]},"fFamily":"Mulish"},{"ch":"B","size":90,"style":"ExtraLight","w":68.5,"data":{"shapes":[{"ty":"gr","it":[{"ind":0,"ty":"sh","ix":1,"ks":{"a":0,"k":{"i":[[0,0],[-4.234,3.367],[0,6.267],[2.866,3],[5.2,0.667],[0,0],[-2.6,2.934],[0,4.334],[4.1,3.2],[7.6,0],[0,0],[0,0]],"o":[[7.666,0],[4.233,-3.366],[0,-4.933],[-2.867,-3],[0,0],[4.533,-1],[2.6,-2.933],[0,-5.8],[-4.1,-3.2],[0,0],[0,0],[0,0]],"v":[[39,0],[56.85,-5.05],[63.2,-19.5],[58.9,-31.4],[46.8,-36.9],[46.8,-35.4],[57.5,-41.3],[61.4,-52.2],[55.25,-65.7],[37.7,-70.5],[8.3,-70.5],[8.3,0]],"c":true},"ix":2},"nm":"B","mn":"ADBE Vector Shape - Group","hd":false},{"ind":1,"ty":"sh","ix":2,"ks":{"a":0,"k":{"i":[[0,0],[0,0],[-2.7,-1.8],[0,-4.266],[2.7,-1.8],[4.733,0],[0,0]],"o":[[0,0],[4.733,0],[2.7,1.8],[0,4.267],[-2.7,1.8],[0,0],[0,0]],"v":[[18.4,-31.7],[37.9,-31.7],[49.05,-29],[53.1,-19.9],[49.05,-10.8],[37.9,-8.1],[18.4,-8.1]],"c":true},"ix":2},"nm":"B","mn":"ADBE Vector Shape - Group","hd":false},{"ind":2,"ty":"sh","ix":3,"ks":{"a":0,"k":{"i":[[0,0],[0,0],[-2.534,-1.933],[0,-3.733],[2.533,-1.933],[5.066,0],[0,0]],"o":[[0,0],[5.066,0],[2.533,1.934],[0,3.734],[-2.534,1.934],[0,0],[0,0]],"v":[[18.4,-62.5],[36.1,-62.5],[47.5,-59.6],[51.3,-51.1],[47.5,-42.6],[36.1,-39.7],[18.4,-39.7]],"c":true},"ix":2},"nm":"B","mn":"ADBE Vector Shape - Group","hd":false}],"nm":"B","np":6,"cix":2,"bm":0,"ix":1,"mn":"ADBE Vector Group","hd":false}]},"fFamily":"Mulish"},{"ch":"h","size":90,"style":"ExtraLight","w":59.3,"data":{"shapes":[{"ty":"gr","it":[{"ind":0,"ty":"sh","ix":1,"ks":{"a":0,"k":{"i":[[0,0],[0,0],[-2.567,2.634],[-4.267,0],[-1.7,-1.966],[0,-4.333],[0,0],[0,0],[0,0],[2.933,3.3],[6,0],[3.266,-1.966],[1.466,-3.8],[0,0],[0,0],[0,0],[0,0]],"o":[[0,0],[0,-4.333],[2.566,-2.633],[3.666,0],[1.7,1.967],[0,0],[0,0],[0,0],[0,-6.666],[-2.934,-3.3],[-4.267,0],[-3.267,1.967],[0,0],[0,0],[0,0],[0,0],[0,0]],"v":[[17.5,0],[17.5,-28.8],[21.35,-39.25],[31.6,-43.2],[39.65,-40.25],[42.2,-30.8],[42.2,0],[52.3,0],[52.3,-31.4],[47.9,-46.35],[34.5,-51.3],[23.2,-48.35],[16.1,-39.7],[17.5,-39.7],[17.5,-73.6],[7.4,-73.6],[7.4,0]],"c":true},"ix":2},"nm":"h","mn":"ADBE Vector Shape - Group","hd":false}],"nm":"h","np":3,"cix":2,"bm":0,"ix":1,"mn":"ADBE Vector Group","hd":false}]},"fFamily":"Mulish"},{"ch":"?","size":90,"style":"ExtraLight","w":46.3,"data":{"shapes":[{"ty":"gr","it":[{"ind":0,"ty":"sh","ix":1,"ks":{"a":0,"k":{"i":[[0,0],[0,0],[-1.3,2.334],[-3.267,3.134],[-1.4,1.934],[-0.734,2],[0,2.134],[1.7,2.334],[3,1.167],[3.8,0],[2.766,-0.633],[2.266,-1.2],[0,0],[-2.467,0.734],[-2.6,0],[-1.934,-1.466],[0,-2.6],[1,-1.966],[2.466,-2.666],[1.233,-2.866],[0,-3.2],[0,0]],"o":[[0,0],[0.266,-2.4],[1.3,-2.333],[2.133,-2.066],[1.4,-1.933],[0.733,-2],[0,-3.533],[-1.7,-2.333],[-3,-1.166],[-2.8,0],[-2.767,0.634],[0,0],[2.2,-1.266],[2.466,-0.733],[3.333,0],[1.933,1.467],[0,2.067],[-1,1.967],[-3.134,3.4],[-1.234,2.867],[0,0],[0,0]],"v":[[23.4,-19.5],[23.8,-22.2],[26.15,-29.3],[33,-37.5],[38.3,-43.5],[41.5,-49.4],[42.6,-55.6],[40.05,-64.4],[33,-69.65],[22.8,-71.4],[14.45,-70.45],[6.9,-67.7],[6.9,-58.7],[13.9,-61.7],[21.5,-62.8],[29.4,-60.6],[32.3,-54.5],[30.8,-48.45],[25.6,-41.5],[19.05,-32.1],[17.2,-23],[17.2,-19.5]],"c":true},"ix":2},"nm":"?","mn":"ADBE Vector Shape - Group","hd":false},{"ind":1,"ty":"sh","ix":2,"ks":{"a":0,"k":{"i":[[0,0],[0,0],[0,0],[0,0]],"o":[[0,0],[0,0],[0,0],[0,0]],"v":[[26.3,0],[26.3,-11.9],[14.3,-11.9],[14.3,0]],"c":true},"ix":2},"nm":"?","mn":"ADBE Vector Shape - Group","hd":false}],"nm":"?","np":5,"cix":2,"bm":0,"ix":1,"mn":"ADBE Vector Group","hd":false}]},"fFamily":"Mulish"},{"ch":"\r","size":90,"style":"ExtraLight","w":0,"fFamily":"Mulish"},{"ch":"C","size":90,"style":"ExtraLight","w":66.3,"data":{"shapes":[{"ty":"gr","it":[{"ind":0,"ty":"sh","ix":1,"ks":{"a":0,"k":{"i":[[-3.934,1.5],[-2.934,2.8],[0,0],[3.033,-1.2],[4,0],[4,4.7],[0,8.6],[-4,4.667],[-7.6,0],[-3.034,-1.2],[-3.2,-2.733],[0,0],[3.933,1.467],[5,0],[5.066,-2.933],[2.7,-5.4],[0,-7.4],[-2.7,-5.433],[-5.067,-2.933],[-7.2,0]],"o":[[3.933,-1.5],[0,0],[-3.2,2.8],[-3.034,1.2],[-7.6,0],[-4,-4.7],[0,-8.6],[4,-4.666],[4,0],[3.033,1.2],[0,0],[-2.934,-2.8],[-3.934,-1.466],[-7.2,0],[-5.067,2.934],[-2.7,5.4],[0,7.4],[2.7,5.434],[5.066,2.934],[5,0]],"v":[[53.4,-1.35],[63.7,-7.8],[60.1,-16.1],[50.75,-10.1],[40.2,-8.3],[22.8,-15.35],[16.8,-35.3],[22.8,-55.2],[40.2,-62.2],[50.75,-60.4],[60.1,-54.5],[63.7,-62.8],[53.4,-69.2],[40,-71.4],[21.6,-67],[9.95,-54.5],[5.9,-35.3],[9.95,-16.05],[21.6,-3.5],[40,0.9]],"c":true},"ix":2},"nm":"C","mn":"ADBE Vector Shape - Group","hd":false}],"nm":"C","np":3,"cix":2,"bm":0,"ix":1,"mn":"ADBE Vector Group","hd":false}]},"fFamily":"Mulish"},{"ch":"l","size":90,"style":"ExtraLight","w":24.9,"data":{"shapes":[{"ty":"gr","it":[{"ind":0,"ty":"sh","ix":1,"ks":{"a":0,"k":{"i":[[0,0],[0,0],[0,0],[0,0]],"o":[[0,0],[0,0],[0,0],[0,0]],"v":[[17.5,0],[17.5,-73.6],[7.4,-73.6],[7.4,0]],"c":true},"ix":2},"nm":"l","mn":"ADBE Vector Shape - Group","hd":false}],"nm":"l","np":3,"cix":2,"bm":0,"ix":1,"mn":"ADBE Vector Group","hd":false}]},"fFamily":"Mulish"},{"ch":"I","size":90,"style":"ExtraLight","w":27,"data":{"shapes":[{"ty":"gr","it":[{"ind":0,"ty":"sh","ix":1,"ks":{"a":0,"k":{"i":[[0,0],[0,0],[0,0],[0,0]],"o":[[0,0],[0,0],[0,0],[0,0]],"v":[[18.7,0],[18.7,-70.5],[8.3,-70.5],[8.3,0]],"c":true},"ix":2},"nm":"I","mn":"ADBE Vector Shape - Group","hd":false}],"nm":"I","np":3,"cix":2,"bm":0,"ix":1,"mn":"ADBE Vector Group","hd":false}]},"fFamily":"Mulish"},{"ch":"t","size":90,"style":"ExtraLight","w":34.3,"data":{"shapes":[{"ty":"gr","it":[{"ind":0,"ty":"sh","ix":1,"ks":{"a":0,"k":{"i":[[-1.334,0.233],[-1,0.4],[0,0],[0.966,-0.233],[1.266,0],[1.333,1.6],[0,3.734],[0,0],[0,0],[0,0],[0,0],[0,0],[0,0],[0,0],[0,0],[0,0],[0,0],[0,0],[-2.8,-2.966],[-5.467,0]],"o":[[1.333,-0.234],[0,0],[-0.8,0.334],[-0.967,0.234],[-2.534,0],[-1.334,-1.6],[0,0],[0,0],[0,0],[0,0],[0,0],[0,0],[0,0],[0,0],[0,0],[0,0],[0,0],[0,5.934],[2.8,2.967],[1.2,0]],"v":[[30.8,0.55],[34.3,-0.4],[34.3,-8.6],[31.65,-7.75],[28.3,-7.4],[22.5,-9.8],[20.5,-17.8],[20.5,-42.6],[34.5,-42.6],[34.5,-50.4],[20.5,-50.4],[20.5,-66.4],[10.4,-63.7],[10.4,-50.4],[0.6,-50.4],[0.6,-42.6],[10.4,-42.6],[10.4,-16.9],[14.6,-3.55],[27,0.9]],"c":true},"ix":2},"nm":"t","mn":"ADBE Vector Shape - Group","hd":false}],"nm":"t","np":3,"cix":2,"bm":0,"ix":1,"mn":"ADBE Vector Group","hd":false}]},"fFamily":"Mulish"}]}